Metadata-Version: 2.1
Name: NeuNetMlp
Version: 0.0.4
Summary: A Multilayered Perceptron Nueral Network Implemented In Python & Numpy
Home-page: 
Author: Pranav Sai
Author-email: pranavs31899@gmail.com
License: MIT
Keywords: Neural Network,Multi-Layered Perceptron
Platform: UNKNOWN
Classifier: Development Status :: 5 - Production/Stable
Classifier: Intended Audience :: Education
Classifier: Operating System :: Microsoft :: Windows :: Windows 10
Classifier: License :: OSI Approved :: MIT License
Classifier: Programming Language :: Python :: 3
License-File: LICENCE.txt
